cond/__init__.py
cond/cond.py
cond-1.2.5.dist-info/LICENSE
cond-1.2.5.dist-info/METADATA
cond-1.2.5.dist-info/WHEEL
cond-1.2.5.dist-info/top_level.txt
cond-1.2.5.dist-info/RECORD
