Metadata-Version: 2.1
Name: cond
Version: 1.2.5
Summary: Custom numeric data type for Python 3 with some additional properties
Home-page: https://github.com/notTypecast/cond
Author: Nick K
Author-email: ynkodizzy@gmail.com
License: UNKNOWN
Platform: UNKNOWN
Classifier: Programming Language :: Python :: 3
Classifier: License :: OSI Approved :: MIT License
Classifier: Operating System :: OS Independent
Requires-Python: >=3.6
